{
  "timestamp": "2023-08-07T20:21:52",
  "compiler": {
    "name": "@stencil/core",
    "version": "4.0.3",
    "typescriptVersion": "5.0.4"
  },
  "components": [
    {
      "filePath": "src/components/c-avatar/c-avatar.tsx",
      "encapsulation": "shadow",
      "tag": "c-avatar",
      "readme": "# c-avatar\n\n\n",
      "docs": "",
      "docsTags": [],
      "usage": {},
      "props": [
        {
          "name": "alt",
          "type": "string",
          "complexType": {
            "original": "string",
            "resolved": "string",
            "references": {}
          },
          "mutable": false,
          "attr": "alt",
          "reflectToAttr": false,
          "docs": "",
          "docsTags": [],
          "default": "''",
          "values": [
            {
              "type": "string"
            }
          ],
          "optional": false,
          "required": false
        },
        {
          "name": "size",
          "type": "string",
          "complexType": {
            "original": "string",
            "resolved": "string",
            "references": {}
          },
          "mutable": false,
          "attr": "size",
          "reflectToAttr": false,
          "docs": "",
          "docsTags": [],
          "default": "'md'",
          "values": [
            {
              "type": "string"
            }
          ],
          "optional": false,
          "required": false
        },
        {
          "name": "src",
          "type": "string",
          "complexType": {
            "original": "string",
            "resolved": "string",
            "references": {}
          },
          "mutable": false,
          "attr": "src",
          "reflectToAttr": false,
          "docs": "",
          "docsTags": [],
          "default": "''",
          "values": [
            {
              "type": "string"
            }
          ],
          "optional": false,
          "required": false
        },
        {
          "name": "text",
          "type": "string",
          "complexType": {
            "original": "string",
            "resolved": "string",
            "references": {}
          },
          "mutable": false,
          "attr": "text",
          "reflectToAttr": false,
          "docs": "",
          "docsTags": [],
          "default": "''",
          "values": [
            {
              "type": "string"
            }
          ],
          "optional": false,
          "required": false
        },
        {
          "name": "variant",
          "type": "string",
          "complexType": {
            "original": "string",
            "resolved": "string",
            "references": {}
          },
          "mutable": false,
          "attr": "variant",
          "reflectToAttr": false,
          "docs": "",
          "docsTags": [],
          "default": "'circle'",
          "values": [
            {
              "type": "string"
            }
          ],
          "optional": false,
          "required": false
        }
      ],
      "methods": [],
      "events": [],
      "listeners": [],
      "styles": [],
      "slots": [],
      "parts": [],
      "dependents": [],
      "dependencies": [],
      "dependencyGraph": {}
    },
    {
      "filePath": "src/components/c-badge/c-badge.tsx",
      "encapsulation": "shadow",
      "tag": "c-badge",
      "readme": "# c-badge\n\n\n",
      "docs": "",
      "docsTags": [],
      "usage": {},
      "props": [
        {
          "name": "size",
          "type": "string",
          "complexType": {
            "original": "string",
            "resolved": "string",
            "references": {}
          },
          "mutable": false,
          "attr": "size",
          "reflectToAttr": false,
          "docs": "",
          "docsTags": [],
          "default": "'sm'",
          "values": [
            {
              "type": "string"
            }
          ],
          "optional": false,
          "required": false
        },
        {
          "name": "type",
          "type": "string",
          "complexType": {
            "original": "string",
            "resolved": "string",
            "references": {}
          },
          "mutable": false,
          "attr": "type",
          "reflectToAttr": false,
          "docs": "",
          "docsTags": [],
          "default": "'default'",
          "values": [
            {
              "type": "string"
            }
          ],
          "optional": false,
          "required": false
        },
        {
          "name": "variant",
          "type": "string",
          "complexType": {
            "original": "string",
            "resolved": "string",
            "references": {}
          },
          "mutable": false,
          "attr": "variant",
          "reflectToAttr": false,
          "docs": "",
          "docsTags": [],
          "default": "'default'",
          "values": [
            {
              "type": "string"
            }
          ],
          "optional": false,
          "required": false
        }
      ],
      "methods": [],
      "events": [],
      "listeners": [],
      "styles": [],
      "slots": [],
      "parts": [],
      "dependents": [],
      "dependencies": [],
      "dependencyGraph": {}
    },
    {
      "filePath": "src/components/c-button/c-button.tsx",
      "encapsulation": "shadow",
      "tag": "c-button",
      "readme": "# c-button\n\n\n",
      "docs": "",
      "docsTags": [],
      "usage": {},
      "props": [
        {
          "name": "appendIcon",
          "type": "string",
          "complexType": {
            "original": "string",
            "resolved": "string",
            "references": {}
          },
          "mutable": false,
          "attr": "append-icon",
          "reflectToAttr": false,
          "docs": "",
          "docsTags": [],
          "default": "''",
          "values": [
            {
              "type": "string"
            }
          ],
          "optional": false,
          "required": false
        },
        {
          "name": "classIcon",
          "type": "string",
          "complexType": {
            "original": "string",
            "resolved": "string",
            "references": {}
          },
          "mutable": false,
          "attr": "class-icon",
          "reflectToAttr": false,
          "docs": "",
          "docsTags": [],
          "default": "'h-4 w-4'",
          "values": [
            {
              "type": "string"
            }
          ],
          "optional": false,
          "required": false
        },
        {
          "name": "disabled",
          "type": "boolean",
          "complexType": {
            "original": "boolean",
            "resolved": "boolean",
            "references": {}
          },
          "mutable": false,
          "attr": "disabled",
          "reflectToAttr": false,
          "docs": "",
          "docsTags": [],
          "default": "false",
          "values": [
            {
              "type": "boolean"
            }
          ],
          "optional": false,
          "required": false
        },
        {
          "name": "prependIcon",
          "type": "string",
          "complexType": {
            "original": "string",
            "resolved": "string",
            "references": {}
          },
          "mutable": false,
          "attr": "prepend-icon",
          "reflectToAttr": false,
          "docs": "",
          "docsTags": [],
          "default": "''",
          "values": [
            {
              "type": "string"
            }
          ],
          "optional": false,
          "required": false
        },
        {
          "name": "size",
          "type": "string",
          "complexType": {
            "original": "string",
            "resolved": "string",
            "references": {}
          },
          "mutable": false,
          "attr": "size",
          "reflectToAttr": false,
          "docs": "",
          "docsTags": [],
          "default": "'md'",
          "values": [
            {
              "type": "string"
            }
          ],
          "optional": false,
          "required": false
        },
        {
          "name": "variant",
          "type": "string",
          "complexType": {
            "original": "string",
            "resolved": "string",
            "references": {}
          },
          "mutable": false,
          "attr": "variant",
          "reflectToAttr": false,
          "docs": "",
          "docsTags": [],
          "default": "'default'",
          "values": [
            {
              "type": "string"
            }
          ],
          "optional": false,
          "required": false
        }
      ],
      "methods": [],
      "events": [],
      "listeners": [],
      "styles": [],
      "slots": [],
      "parts": [],
      "dependents": [],
      "dependencies": [
        "c-icon"
      ],
      "dependencyGraph": {
        "c-button": [
          "c-icon"
        ]
      }
    },
    {
      "filePath": "src/components/c-card/c-card.tsx",
      "encapsulation": "shadow",
      "tag": "c-card",
      "readme": "# c-card\n\n\n",
      "docs": "",
      "docsTags": [],
      "usage": {},
      "props": [
        {
          "name": "description",
          "type": "string",
          "complexType": {
            "original": "string",
            "resolved": "string",
            "references": {}
          },
          "mutable": false,
          "attr": "description",
          "reflectToAttr": false,
          "docs": "",
          "docsTags": [],
          "values": [
            {
              "type": "string"
            }
          ],
          "optional": false,
          "required": false
        },
        {
          "name": "footer",
          "type": "string",
          "complexType": {
            "original": "string",
            "resolved": "string",
            "references": {}
          },
          "mutable": false,
          "attr": "footer",
          "reflectToAttr": false,
          "docs": "",
          "docsTags": [],
          "values": [
            {
              "type": "string"
            }
          ],
          "optional": false,
          "required": false
        },
        {
          "name": "subtitle",
          "type": "string",
          "complexType": {
            "original": "string",
            "resolved": "string",
            "references": {}
          },
          "mutable": false,
          "attr": "subtitle",
          "reflectToAttr": false,
          "docs": "",
          "docsTags": [],
          "values": [
            {
              "type": "string"
            }
          ],
          "optional": false,
          "required": false
        },
        {
          "name": "title",
          "type": "string",
          "complexType": {
            "original": "string",
            "resolved": "string",
            "references": {}
          },
          "mutable": false,
          "attr": "title",
          "reflectToAttr": false,
          "docs": "",
          "docsTags": [],
          "values": [
            {
              "type": "string"
            }
          ],
          "optional": false,
          "required": false
        }
      ],
      "methods": [],
      "events": [],
      "listeners": [],
      "styles": [],
      "slots": [],
      "parts": [],
      "dependents": [
        "c-playground"
      ],
      "dependencies": [],
      "dependencyGraph": {
        "c-playground": [
          "c-card"
        ]
      }
    },
    {
      "filePath": "src/components/c-checkbox/c-checkbox.tsx",
      "encapsulation": "shadow",
      "tag": "c-checkbox",
      "readme": "# c-checkbox\n\n\n",
      "docs": "",
      "docsTags": [],
      "usage": {},
      "props": [
        {
          "name": "checked",
          "type": "boolean",
          "complexType": {
            "original": "boolean",
            "resolved": "boolean",
            "references": {}
          },
          "mutable": false,
          "attr": "checked",
          "reflectToAttr": false,
          "docs": "",
          "docsTags": [],
          "default": "false",
          "values": [
            {
              "type": "boolean"
            }
          ],
          "optional": false,
          "required": false
        },
        {
          "name": "description",
          "type": "string",
          "complexType": {
            "original": "string",
            "resolved": "string",
            "references": {}
          },
          "mutable": false,
          "attr": "description",
          "reflectToAttr": false,
          "docs": "",
          "docsTags": [],
          "values": [
            {
              "type": "string"
            }
          ],
          "optional": false,
          "required": false
        },
        {
          "name": "disabled",
          "type": "boolean",
          "complexType": {
            "original": "boolean",
            "resolved": "boolean",
            "references": {}
          },
          "mutable": true,
          "attr": "disabled",
          "reflectToAttr": false,
          "docs": "",
          "docsTags": [],
          "default": "false",
          "values": [
            {
              "type": "boolean"
            }
          ],
          "optional": false,
          "required": false
        }
      ],
      "methods": [],
      "events": [],
      "listeners": [],
      "styles": [],
      "slots": [],
      "parts": [],
      "dependents": [],
      "dependencies": [
        "c-icon",
        "c-label"
      ],
      "dependencyGraph": {
        "c-checkbox": [
          "c-icon",
          "c-label"
        ]
      }
    },
    {
      "filePath": "src/components/c-icon/c-icon.tsx",
      "encapsulation": "shadow",
      "tag": "c-icon",
      "readme": "# c-icon\n\n\n",
      "docs": "",
      "docsTags": [],
      "usage": {},
      "props": [
        {
          "name": "class",
          "type": "string",
          "complexType": {
            "original": "string",
            "resolved": "string",
            "references": {}
          },
          "mutable": false,
          "attr": "class",
          "reflectToAttr": true,
          "docs": "",
          "docsTags": [],
          "default": "'h-4 w-4'",
          "values": [
            {
              "type": "string"
            }
          ],
          "optional": false,
          "required": false
        },
        {
          "name": "color",
          "type": "string",
          "complexType": {
            "original": "string",
            "resolved": "string",
            "references": {}
          },
          "mutable": false,
          "attr": "color",
          "reflectToAttr": false,
          "docs": "",
          "docsTags": [],
          "default": "'currentColor'",
          "values": [
            {
              "type": "string"
            }
          ],
          "optional": false,
          "required": false
        },
        {
          "name": "name",
          "type": "string",
          "complexType": {
            "original": "string",
            "resolved": "string",
            "references": {}
          },
          "mutable": false,
          "attr": "name",
          "reflectToAttr": false,
          "docs": "",
          "docsTags": [],
          "default": "'circle'",
          "values": [
            {
              "type": "string"
            }
          ],
          "optional": false,
          "required": false
        },
        {
          "name": "size",
          "type": "string",
          "complexType": {
            "original": "string",
            "resolved": "string",
            "references": {}
          },
          "mutable": false,
          "attr": "size",
          "reflectToAttr": false,
          "docs": "",
          "docsTags": [],
          "default": "'24px'",
          "values": [
            {
              "type": "string"
            }
          ],
          "optional": false,
          "required": false
        },
        {
          "name": "strokeWidth",
          "type": "string",
          "complexType": {
            "original": "string",
            "resolved": "string",
            "references": {}
          },
          "mutable": false,
          "attr": "stroke-width",
          "reflectToAttr": false,
          "docs": "",
          "docsTags": [],
          "default": "'2px'",
          "values": [
            {
              "type": "string"
            }
          ],
          "optional": false,
          "required": false
        }
      ],
      "methods": [],
      "events": [],
      "listeners": [],
      "styles": [],
      "slots": [],
      "parts": [],
      "dependents": [
        "c-button",
        "c-checkbox"
      ],
      "dependencies": [],
      "dependencyGraph": {
        "c-button": [
          "c-icon"
        ],
        "c-checkbox": [
          "c-icon"
        ]
      }
    },
    {
      "filePath": "src/components/c-input/c-input.tsx",
      "encapsulation": "shadow",
      "tag": "c-input",
      "readme": "# c-input\n\n\n",
      "docs": "",
      "docsTags": [],
      "usage": {},
      "props": [
        {
          "name": "disabled",
          "type": "boolean",
          "complexType": {
            "original": "boolean",
            "resolved": "boolean",
            "references": {}
          },
          "mutable": false,
          "attr": "disabled",
          "reflectToAttr": false,
          "docs": "",
          "docsTags": [],
          "default": "false",
          "values": [
            {
              "type": "boolean"
            }
          ],
          "optional": false,
          "required": false
        },
        {
          "name": "label",
          "type": "string",
          "complexType": {
            "original": "string",
            "resolved": "string",
            "references": {}
          },
          "mutable": false,
          "attr": "label",
          "reflectToAttr": false,
          "docs": "",
          "docsTags": [],
          "default": "''",
          "values": [
            {
              "type": "string"
            }
          ],
          "optional": false,
          "required": false
        },
        {
          "name": "max",
          "type": "string",
          "complexType": {
            "original": "string",
            "resolved": "string",
            "references": {}
          },
          "mutable": false,
          "attr": "max",
          "reflectToAttr": false,
          "docs": "",
          "docsTags": [],
          "default": "''",
          "values": [
            {
              "type": "string"
            }
          ],
          "optional": false,
          "required": false
        },
        {
          "name": "min",
          "type": "string",
          "complexType": {
            "original": "string",
            "resolved": "string",
            "references": {}
          },
          "mutable": false,
          "attr": "min",
          "reflectToAttr": false,
          "docs": "",
          "docsTags": [],
          "default": "''",
          "values": [
            {
              "type": "string"
            }
          ],
          "optional": false,
          "required": false
        },
        {
          "name": "placeholder",
          "type": "string",
          "complexType": {
            "original": "string",
            "resolved": "string",
            "references": {}
          },
          "mutable": false,
          "attr": "placeholder",
          "reflectToAttr": false,
          "docs": "",
          "docsTags": [],
          "default": "'Placeholder'",
          "values": [
            {
              "type": "string"
            }
          ],
          "optional": false,
          "required": false
        },
        {
          "name": "readonly",
          "type": "boolean",
          "complexType": {
            "original": "boolean",
            "resolved": "boolean",
            "references": {}
          },
          "mutable": false,
          "attr": "readonly",
          "reflectToAttr": false,
          "docs": "",
          "docsTags": [],
          "default": "false",
          "values": [
            {
              "type": "boolean"
            }
          ],
          "optional": false,
          "required": false
        },
        {
          "name": "required",
          "type": "boolean",
          "complexType": {
            "original": "boolean",
            "resolved": "boolean",
            "references": {}
          },
          "mutable": false,
          "attr": "required",
          "reflectToAttr": false,
          "docs": "",
          "docsTags": [],
          "default": "false",
          "values": [
            {
              "type": "boolean"
            }
          ],
          "optional": false,
          "required": false
        },
        {
          "name": "step",
          "type": "string",
          "complexType": {
            "original": "string",
            "resolved": "string",
            "references": {}
          },
          "mutable": false,
          "attr": "step",
          "reflectToAttr": false,
          "docs": "",
          "docsTags": [],
          "default": "''",
          "values": [
            {
              "type": "string"
            }
          ],
          "optional": false,
          "required": false
        },
        {
          "name": "type",
          "type": "string",
          "complexType": {
            "original": "string",
            "resolved": "string",
            "references": {}
          },
          "mutable": false,
          "attr": "type",
          "reflectToAttr": false,
          "docs": "",
          "docsTags": [],
          "default": "'text'",
          "values": [
            {
              "type": "string"
            }
          ],
          "optional": false,
          "required": false
        },
        {
          "name": "value",
          "type": "string",
          "complexType": {
            "original": "string",
            "resolved": "string",
            "references": {}
          },
          "mutable": false,
          "attr": "value",
          "reflectToAttr": false,
          "docs": "",
          "docsTags": [],
          "default": "''",
          "values": [
            {
              "type": "string"
            }
          ],
          "optional": false,
          "required": false
        }
      ],
      "methods": [],
      "events": [],
      "listeners": [],
      "styles": [],
      "slots": [],
      "parts": [],
      "dependents": [
        "c-playground"
      ],
      "dependencies": [
        "c-label"
      ],
      "dependencyGraph": {
        "c-input": [
          "c-label"
        ],
        "c-playground": [
          "c-input"
        ]
      }
    },
    {
      "filePath": "src/components/c-label/c-label.tsx",
      "encapsulation": "shadow",
      "tag": "c-label",
      "readme": "# c-label\n\n\n",
      "docs": "",
      "docsTags": [],
      "usage": {},
      "props": [
        {
          "name": "htmlFor",
          "type": "string",
          "complexType": {
            "original": "string",
            "resolved": "string",
            "references": {}
          },
          "mutable": false,
          "attr": "html-for",
          "reflectToAttr": false,
          "docs": "",
          "docsTags": [],
          "default": "'input'",
          "values": [
            {
              "type": "string"
            }
          ],
          "optional": false,
          "required": false
        }
      ],
      "methods": [],
      "events": [],
      "listeners": [],
      "styles": [],
      "slots": [],
      "parts": [],
      "dependents": [
        "c-checkbox",
        "c-input"
      ],
      "dependencies": [],
      "dependencyGraph": {
        "c-checkbox": [
          "c-label"
        ],
        "c-input": [
          "c-label"
        ]
      }
    },
    {
      "filePath": "src/components/c-playground/c-playground.tsx",
      "encapsulation": "shadow",
      "tag": "c-playground",
      "readme": "# c-playground\n\n\n",
      "docs": "",
      "docsTags": [],
      "usage": {},
      "props": [],
      "methods": [],
      "events": [],
      "listeners": [],
      "styles": [],
      "slots": [],
      "parts": [],
      "dependents": [],
      "dependencies": [
        "c-card",
        "c-input"
      ],
      "dependencyGraph": {
        "c-playground": [
          "c-card",
          "c-input"
        ],
        "c-input": [
          "c-label"
        ]
      }
    },
    {
      "filePath": "src/components/c-provider/c-provider.tsx",
      "encapsulation": "none",
      "tag": "c-provider",
      "readme": "# c-provider\n\n\n",
      "docs": "",
      "docsTags": [],
      "usage": {},
      "props": [],
      "methods": [],
      "events": [],
      "listeners": [],
      "styles": [],
      "slots": [],
      "parts": [],
      "dependents": [],
      "dependencies": [],
      "dependencyGraph": {}
    }
  ],
  "typeLibrary": {}
}